Metadata-Version: 1.1
Name: s3cache
Version: 0.1.0
Summary: Local cache of S3 buckets
Home-page: https://github.com/vincetse/python-s3-cache
Author: Vince Tse, based on work by Niall McCarroll
Author-email: thelazyenginerd@gmail.com
License: UNKNOWN
Keywords: aws,s3,cache
Platform: UNKNOWN
Classifier: Development Status :: 5 - Production/Stable
Classifier: Intended Audience :: Developers
Classifier: Natural Language :: English
Classifier: Operating System :: OS Independent
Classifier: Programming Language :: Python
Classifier: Programming Language :: Python :: 2.7
Classifier: Topic :: System :: Filesystems
